voc_builder/__init__.py
voc_builder/builder/__init__.py
voc_builder/builder/ai_svc.py
voc_builder/builder/models.py
voc_builder/builder/serializers.py
voc_builder/builder/views.py
voc_builder/commands/__init__.py
voc_builder/commands/export.py
voc_builder/common/__init__.py
voc_builder/common/errors.py
voc_builder/common/text.py
voc_builder/common/web/__init__.py
voc_builder/common/web/std_err.py
voc_builder/exceptions.py
voc_builder/infras/ai.py
voc_builder/infras/config.py
voc_builder/infras/store.py
voc_builder/learn/ai_svc.py
voc_builder/learn/serializers.py
voc_builder/learn/views.py
voc_builder/main.py
voc_builder/misc/__init__.py
voc_builder/misc/export.py
voc_builder/misc/version.py
voc_builder/notepad/__init__.py
voc_builder/notepad/dist/assets/LearnNav-e2a42dec.js
voc_builder/notepad/dist/assets/LearnView-333542d6.js
voc_builder/notepad/dist/assets/LearnView-7ecae183.css
voc_builder/notepad/dist/assets/MasteredWordsView-68c17975.js
voc_builder/notepad/dist/assets/MasteredWordsView-fac8ca1d.css
voc_builder/notepad/dist/assets/QuizView-1422d2ad.js
voc_builder/notepad/dist/assets/QuizView-311f979b.css
voc_builder/notepad/dist/assets/Settings-f3dc2007.js
voc_builder/notepad/dist/assets/StoryView-65beec43.js
voc_builder/notepad/dist/assets/StoryView-9030aa50.css
voc_builder/notepad/dist/assets/ai-voc-logo-36f100c2.png
voc_builder/notepad/dist/assets/bootstrap-icons-999550fa.woff
voc_builder/notepad/dist/assets/bootstrap-icons-cfe45b98.woff2
voc_builder/notepad/dist/assets/index-99739378.js
voc_builder/notepad/dist/assets/index-a1b28d7f.css
voc_builder/notepad/dist/index.html
voc_builder/notepad/server.py
voc_builder/system/constants.py
voc_builder/system/language.py
voc_builder/system/models.py
voc_builder/system/serializers.py
voc_builder/system/views.py
ai_vocabulary_builder-1.4.1.dist-info/LICENSE
ai_vocabulary_builder-1.4.1.dist-info/METADATA
ai_vocabulary_builder-1.4.1.dist-info/WHEEL
ai_vocabulary_builder-1.4.1.dist-info/entry_points.txt
ai_vocabulary_builder-1.4.1.dist-info/RECORD
