Metadata-Version: 2.3
Name: ai-vocabulary-builder
Version: 1.4.1
Summary: An AI-powered smart vocabulary tool with features like One-click vocabulary building and story-based memorization.
Author: piglei
Author-email: piglei2007@gmail.com
Requires-Python: >=3.10,<4.0
Classifier: Programming Language :: Python :: 3
Classifier: Programming Language :: Python :: 3.10
Classifier: Programming Language :: Python :: 3.11
Classifier: Programming Language :: Python :: 3.12
Classifier: Programming Language :: Python :: 3.13
Requires-Dist: cattrs (>=24.1.2,<25.0.0)
Requires-Dist: click (>=8.0.0,<9.0.0)
Requires-Dist: fastapi (>=0.115.6,<0.116.0)
Requires-Dist: genanki (>=0.13.1,<0.14.0)
Requires-Dist: packaging (>=23.0,<24.0)
Requires-Dist: pydantic-ai (>=1.18.0,<2.0.0)
Requires-Dist: requests (>=2.32.3,<3.0.0)
Requires-Dist: rich (>=13.0.0,<14.0.0)
Requires-Dist: sse-starlette (>=1.3.4,<2.0.0)
Requires-Dist: tinydb (>=4.7.1,<5.0.0)
Requires-Dist: unearth (>=0.17.2,<0.18.0)
Requires-Dist: uvicorn (>=0.38.0,<0.39.0)
